bonsai/__init__.py
bonsai/asyncio_event_loop.py
bonsai/bonsai_logging.py
bonsai/brain.py
bonsai/brain_server_connection.py
bonsai/connections.py
bonsai/drivers.py
bonsai/generator.py
bonsai/grpc_event_loop.py
bonsai/inkling_types.py
bonsai/protocols.py
bonsai/simulator.py
bonsai/test_brain_server_connection.py
bonsai/test_drivers.py
bonsai/tornado_event_loop.py
bonsai/websocket_event_loop.py
bonsai/common/__init__.py
bonsai/common/message_builder.py
bonsai/common/state_to_proto.py
bonsai/common/test_message_builder.py
bonsai/common/test_state_to_proto.py
bonsai/common/test_utils.py
bonsai/common/utils.py
bonsai/proto/__init__.py
bonsai/proto/curve_generator_pb2.py
bonsai/proto/generator_simulator_api_pb2.py
bonsai/proto/inkling_types_pb2.py
bonsai/proto/instructor_api_pb2.py
bonsai/proto/instructor_api_pb2_grpc.py
bonsai_python-0.13.5.dist-info/DESCRIPTION.rst
bonsai_python-0.13.5.dist-info/METADATA
bonsai_python-0.13.5.dist-info/RECORD
bonsai_python-0.13.5.dist-info/WHEEL
bonsai_python-0.13.5.dist-info/metadata.json
bonsai_python-0.13.5.dist-info/top_level.txt
