Metadata-Version: 2.0
Name: bonsai-python
Version: 0.13.5
Summary: A library creating and training AIs with Bonsai BRAIN
Home-page: http://github.com/BonsaiAI/bonsai-python
Author: Bonsai Engineering
Author-email: opensource@bons.ai
License: BSD
Keywords: bonsai
Platform: UNKNOWN
Classifier: Development Status :: 4 - Beta
Classifier: Intended Audience :: Developers
Classifier: Topic :: Scientific/Engineering :: Artificial Intelligence
Classifier: License :: OSI Approved :: BSD License
Classifier: Programming Language :: Python :: 2
Classifier: Programming Language :: Python :: 2.7
Classifier: Programming Language :: Python :: 3
Classifier: Programming Language :: Python :: 3.4
Classifier: Programming Language :: Python :: 3.5
Classifier: Natural Language :: English
Requires-Dist: bonsai-config (>=0.3.0)
Requires-Dist: futures (==3.1.1)
Requires-Dist: protobuf (<4,>=3.0.0)
Requires-Dist: six (>=1.10.0)
Requires-Dist: tornado (>=4.5.0)
Requires-Dist: websocket-client (>=0.40.0)
Requires-Dist: grpcio (>=1.6.3)
